pulumiverse_exoscale/__init__.py
pulumiverse_exoscale/_inputs.py
pulumiverse_exoscale/_utilities.py
pulumiverse_exoscale/affinity.py
pulumiverse_exoscale/anti_affinity_group.py
pulumiverse_exoscale/block_storage_volume.py
pulumiverse_exoscale/block_storage_volume_snapshot.py
pulumiverse_exoscale/compute.py
pulumiverse_exoscale/compute_instance.py
pulumiverse_exoscale/database.py
pulumiverse_exoscale/domain.py
pulumiverse_exoscale/domain_record.py
pulumiverse_exoscale/elastic_ip.py
pulumiverse_exoscale/get_affinity.py
pulumiverse_exoscale/get_anti_affinity_group.py
pulumiverse_exoscale/get_block_storage_volume.py
pulumiverse_exoscale/get_block_storage_volume_snapshot.py
pulumiverse_exoscale/get_compute.py
pulumiverse_exoscale/get_compute_instance.py
pulumiverse_exoscale/get_compute_instance_list.py
pulumiverse_exoscale/get_compute_ip_address.py
pulumiverse_exoscale/get_compute_template.py
pulumiverse_exoscale/get_database_uri.py
pulumiverse_exoscale/get_domain.py
pulumiverse_exoscale/get_domain_record.py
pulumiverse_exoscale/get_elastic_ip.py
pulumiverse_exoscale/get_iam_api_key.py
pulumiverse_exoscale/get_iam_org_policy.py
pulumiverse_exoscale/get_iam_role.py
pulumiverse_exoscale/get_iamapi_key.py
pulumiverse_exoscale/get_instance_pool.py
pulumiverse_exoscale/get_instance_pool_list.py
pulumiverse_exoscale/get_network.py
pulumiverse_exoscale/get_nlb.py
pulumiverse_exoscale/get_nlb_service_list.py
pulumiverse_exoscale/get_private_network.py
pulumiverse_exoscale/get_security_group.py
pulumiverse_exoscale/get_sks_cluster.py
pulumiverse_exoscale/get_sks_cluster_list.py
pulumiverse_exoscale/get_sks_nodepool.py
pulumiverse_exoscale/get_sks_nodepool_list.py
pulumiverse_exoscale/get_template.py
pulumiverse_exoscale/get_zones.py
pulumiverse_exoscale/iam_access_key.py
pulumiverse_exoscale/iam_api_key.py
pulumiverse_exoscale/iam_org_policy.py
pulumiverse_exoscale/iam_role.py
pulumiverse_exoscale/iamapi_key.py
pulumiverse_exoscale/instance_pool.py
pulumiverse_exoscale-0.0.0.dist-info/METADATA
pulumiverse_exoscale-0.0.0.dist-info/WHEEL
pulumiverse_exoscale-0.0.0.dist-info/top_level.txt
pulumiverse_exoscale-0.0.0.dist-info/RECORD
