Metadata-Version: 2.1
Name: pulumiverse_exoscale
Version: 0.0.0
Summary: A Pulumi package for creating and managing exoscale cloud resources.
Home-page: https://www.pulumi.com
License: Apache-2.0
Project-URL: Repository, https://github.com/pulumiverse/pulumi-exoscale
Keywords: pulumi exoscale category/cloud
Requires-Python: >=3.8
Requires-Dist: parver>=0.2.1
Requires-Dist: pulumi<4.0.0,>=3.0.0
Requires-Dist: semver>=2.8.1
